{"note":"Don't delete this file! It's used internally to help with page regeneration.","body":"#**ADK Pedometer with Thermal Printer**\r\n\r\n\r\n## Features\r\n\r\n----------\r\n**Android application combines Step Counter(aka Pedometer) and ADK protocol. By Yunsu Choi**\r\n\r\n*This application send device's accerometer data to Arduino and Print by using [Thermal Printer](http://www.sparkfun.com/products/10438)*\r\n\r\n\r\n## Installation\r\n\r\n----------\r\n- Build Application and install into your Android Device (version 2.3+)\r\n- Upload the [firmware](https://github.com/YunsuChoi/Pedometer.arduino)\r\n- Make connection with your Thermal Printer\r\n- Connect both side(Arduino/Android) with USB Host Shield\r\n- Enjoy!\r\n\r\n\r\n##License\r\n\r\n---------- \r\n[GNU General Public License, version 3](http://www.gnu.org/licenses/gpl.html)\r\n\r\n\r\n##Links\r\n\r\n----------\r\n- [Working Video in Youtube](http://youtu.be/SXDb_zcgmcM) \r\n- [Thermal Printer](http://www.sparkfun.com/products/10438)\r\n- [USB Host Shield](http://www.circuitsathome.com/mcu/google-open-accessory-interface-for-usb-host-shield-library-2-0-released)\r\n","name":"Pedometer.android","google":"","tagline":"Android code for pedometer"}